odoo/addons/sale_pricelist_global_rule/README.rst
odoo/addons/sale_pricelist_global_rule/__init__.py
odoo/addons/sale_pricelist_global_rule/__manifest__.py
odoo/addons/sale_pricelist_global_rule/i18n/it.po
odoo/addons/sale_pricelist_global_rule/i18n/sale_pricelist_global_rule.pot
odoo/addons/sale_pricelist_global_rule/migrations/17.0.1.0.0/pre-migration.py
odoo/addons/sale_pricelist_global_rule/models/__init__.py
odoo/addons/sale_pricelist_global_rule/models/product_pricelist.py
odoo/addons/sale_pricelist_global_rule/models/sale_order.py
odoo/addons/sale_pricelist_global_rule/models/sale_order_line.py
odoo/addons/sale_pricelist_global_rule/readme/CONFIGURE.md
odoo/addons/sale_pricelist_global_rule/readme/CONTRIBUTORS.md
odoo/addons/sale_pricelist_global_rule/readme/DESCRIPTION.md
odoo/addons/sale_pricelist_global_rule/readme/ROADMAP.md
odoo/addons/sale_pricelist_global_rule/readme/USAGE.md
odoo/addons/sale_pricelist_global_rule/static/description/icon.png
odoo/addons/sale_pricelist_global_rule/static/description/index.html
odoo/addons/sale_pricelist_global_rule/tests/__init__.py
odoo/addons/sale_pricelist_global_rule/tests/test_pricelist_global.py
odoo/addons/sale_pricelist_global_rule/views/product_pricelist_item_views.xml
odoo/addons/sale_pricelist_global_rule/views/sale_order_views.xml
odoo_addon_sale_pricelist_global_rule-17.0.1.0.0.4.dist-info/METADATA
odoo_addon_sale_pricelist_global_rule-17.0.1.0.0.4.dist-info/WHEEL
odoo_addon_sale_pricelist_global_rule-17.0.1.0.0.4.dist-info/top_level.txt
odoo_addon_sale_pricelist_global_rule-17.0.1.0.0.4.dist-info/RECORD
